{
  "id" : "3d3c3424-61cc-4990-8d9c-83887c375116",
  "name" : "Example",
  "description" : "A generic microservices application",
  "version" : "0.2.2-alpha",
  "highTechnologicalRisk" : false,
  "nfrs" : [ {
    "kind" : "availability",
    "tags" : [ "Application" ],
    "quantitativeAvailability" : 97.0,
    "unit" : "percentage"
  }, {
    "kind" : "availability",
    "tags" : [ "Application" ],
    "quantitativeAvailability" : 100.0,
    "unit" : "percentage"
  } ],
  "microservices" : [ {
    "id" : "9d04b29c-b0f4-413d-9f17-ce494d33181d",
    "name" : "example",
    "stateful" : false,
    "tags" : [ "Application" ],
    "publicIP" : false,
    "endpoints" : [ "" ],
    "deploymentOrder" : 0
  } ]
}